trackmania/__init__.py
trackmania/_util.py
trackmania/ad.py
trackmania/api.py
trackmania/config.py
trackmania/constants.py
trackmania/cotd.py
trackmania/errors.py
trackmania/matchmaking.py
trackmania/player.py
trackmania/tmmap.py
trackmania/tmx.py
trackmania/totd.py
trackmania/trophy.py
py_tmio-0.4.6.dist-info/LICENSE
py_tmio-0.4.6.dist-info/METADATA
py_tmio-0.4.6.dist-info/WHEEL
py_tmio-0.4.6.dist-info/top_level.txt
py_tmio-0.4.6.dist-info/RECORD
