Metadata-Version: 2.1
Name: py-tmio
Version: 0.4.6
Summary: Trackmania.io API Wrapper
Home-page: https://github.com/NottCurious/py-tmio
Author: Deepesh Nimma
License: MIT
Project-URL: Documentation, https://py-trackmaniaio.rtfd.io/
Project-URL: Issue Tracker, https://github.com/NottCurious/py-tmio/issues
Platform: UNKNOWN
Classifier: Programming Language :: Python :: 3
Classifier: Programming Language :: Python :: 3.10
Classifier: License :: OSI Approved :: MIT License
Classifier: Operating System :: OS Independent
Requires-Python: >=3.10
License-File: LICENSE
Requires-Dist: aiohttp
Requires-Dist: redis
